qblocal_backup/__init__.py
qblocal_backup/__main__.py
qblocal_backup-0.1.1.dist-info/LICENSE
qblocal_backup-0.1.1.dist-info/WHEEL
qblocal_backup-0.1.1.dist-info/METADATA
qblocal_backup-0.1.1.dist-info/RECORD
